videoipath_automation_tool/__init__.py
videoipath_automation_tool/apps/__init__.py
videoipath_automation_tool/apps/inventory/__init__.py
videoipath_automation_tool/apps/inventory/app/__init__.py
videoipath_automation_tool/apps/inventory/app/app.py
videoipath_automation_tool/apps/inventory/app/create_device.py
videoipath_automation_tool/apps/inventory/app/create_device_from_discovered_device.py
videoipath_automation_tool/apps/inventory/app/get_device.py
videoipath_automation_tool/apps/inventory/inventory_api.py
videoipath_automation_tool/apps/inventory/inventory_utils.py
videoipath_automation_tool/apps/inventory/model/__init__.py
videoipath_automation_tool/apps/inventory/model/device_status.py
videoipath_automation_tool/apps/inventory/model/driver_schema/2023.4.2.json
videoipath_automation_tool/apps/inventory/model/driver_schema/2023.4.35.json
videoipath_automation_tool/apps/inventory/model/driver_schema/2023.4.37.json
videoipath_automation_tool/apps/inventory/model/driver_schema/2024.1.4.json
videoipath_automation_tool/apps/inventory/model/driver_schema/2024.2.10.json
videoipath_automation_tool/apps/inventory/model/driver_schema/2024.2.11.json
videoipath_automation_tool/apps/inventory/model/driver_schema/2024.2.6.json
videoipath_automation_tool/apps/inventory/model/driver_schema/2024.3.3.json
videoipath_automation_tool/apps/inventory/model/driver_schema/2024.4.11.json
videoipath_automation_tool/apps/inventory/model/driver_schema/2024.4.12.json
videoipath_automation_tool/apps/inventory/model/driver_schema/2024.4.14.json
videoipath_automation_tool/apps/inventory/model/driver_schema/2024.4.20.json
videoipath_automation_tool/apps/inventory/model/driver_schema/2024.4.30.json
videoipath_automation_tool/apps/inventory/model/driver_schema/2025.2.0.json
videoipath_automation_tool/apps/inventory/model/driver_schema/2025.3.2.json
videoipath_automation_tool/apps/inventory/model/driver_schema/README.md
videoipath_automation_tool/apps/inventory/model/drivers.py
videoipath_automation_tool-0.7.1.dist-info/METADATA
videoipath_automation_tool-0.7.1.dist-info/WHEEL
videoipath_automation_tool-0.7.1.dist-info/entry_points.txt
videoipath_automation_tool-0.7.1.dist-info/licenses/LICENSE
videoipath_automation_tool-0.7.1.dist-info/RECORD
