Metadata-Version: 2.4
Name: videoipath-automation-tool
Version: 0.7.1
Summary: A Python package for automating VideoIPath configuration workflows.
License-Expression: AGPL-3.0-only
License-File: LICENSE
Keywords: videoipath,automation,nevion,media-over-ip,st2110,orchestration
Author: Paul Winterstein
Author-email: paul.winterstein@swr.de
Maintainer: SWR Media-over-IP Team
Maintainer-email: moip@swr.de
Requires-Python: >=3.11
Classifier: Programming Language :: Python :: 3
Classifier: Programming Language :: Python :: 3.11
Classifier: Programming Language :: Python :: 3.12
Classifier: Programming Language :: Python :: 3.13
Classifier: Programming Language :: Python :: 3.14
Requires-Dist: deepdiff (>=8.6.1,<9.0.0)
Requires-Dist: pydantic (>=2.6.4,<3.0.0)
Requires-Dist: pydantic-extra-types (>=2.6.0,<3.0.0)
Requires-Dist: pydantic-settings (>=2.2.1,<3.0.0)
Requires-Dist: requests (>=2.31.0,<3.0.0)
Requires-Dist: urllib3 (>=2.6.3,<3.0.0)
Project-URL: Documentation, https://github.com/SWR-MoIP/VideoIPath-Automation-Tool#documentation
Project-URL: Homepage, https://github.com/SWR-MoIP/VideoIPath-Automation-Tool
Project-URL: Issues, https://github.com/SWR-MoIP/VideoIPath-Automation-Tool/issues
Project-URL: Repository, https://github.com/SWR-MoIP/VideoIPath-Automation-Tool
